examples/00_timeseries.py
examples/01_grid.py
examples/02_unpivoted_grid.py
examples/03_grid_timeseries.py
examples/04_grid_png.py
examples/05_lighning_strokes.py
examples/06_netcdf.py
examples/07_find_stations.py
examples/08_station_coordinates_timeseries.py
examples/09_station_ids.py
examples/10_get_init_dates.py
examples/11_get_available_time_ranges.py
examples/12_test_account_options.py
examples/13_using_proxy.py
examples/14_raw_api_data.py
examples/__init__.py
examples/credentials.py
examples/energy_market_plots.py
examples/example.py
meteomatics/__init__.py
meteomatics/__version__.py
meteomatics/_constants_.py
meteomatics/api.py
meteomatics/binary_parser.py
meteomatics/binary_reader.py
meteomatics/deprecated.py
meteomatics/exceptions.py
meteomatics/logger.py
meteomatics/parsing_util.py
meteomatics/rounding.py
meteomatics-3.0.0.dist-info/LICENSE
meteomatics-3.0.0.dist-info/METADATA
meteomatics-3.0.0.dist-info/WHEEL
meteomatics-3.0.0.dist-info/top_level.txt
meteomatics-3.0.0.dist-info/RECORD
