Metadata-Version: 2.1
Name: meteomatics
Version: 3.0.0
Summary: Meteomatics API connector
Home-page: https://github.com/meteomatics/python-connector-api
Author: Meteomatics AG
Author-email: support@meteomatics.com
License: MIT
Classifier: License :: OSI Approved :: MIT License
Classifier: Programming Language :: Python
Classifier: Programming Language :: Python :: 3
Requires-Python: >=3.9.0
License-File: LICENSE
Requires-Dist: isodate (>=0.6.0)
Requires-Dist: requests (>=2.21.0)
Requires-Dist: pandas (>=1.1.5)
Requires-Dist: pathlib2 (>=2.3.5)
Requires-Dist: pytz
